main.py
extraction/__init__.py
generalizability/__init__.py
parser/__init__.py
parser/logconf.py
parser/main.py
parser/parse_direct.py
parser/root_pb2.py
parser/extraction/FoundExpression.py
parser/extraction/__init__.py
parser/extraction/extraction.py
parser/extraction/extraction_accuracy.py
parser/extraction/extraction_java.py
parser/extraction/extraction_py.py
parser/testing/__init__.py
parser/testing/basic_subexpression_tests.py
parser/testing/general_tests.py
parser/testing/intermediate_expression_tests.py
parser/testing/intermediate_expression_tests_part2.py
parser/testing/test_utils.py
protobuf/__init__.py
protobuf/python_out/__init__.py
protobuf/python_out/root_pb2.py
security/__init__.py
security/config.py
security/genetic.py
security/mutations.py
security/pb_test.py
security/root_pb2.py
security/seeding.py
security/timing.py
understandability/__init__.py
understandability/root_pb2.py
understandability/test.py
understandability/understandability.py
RegexAnalyzer-0.0.1.dist-info/LICENSE
RegexAnalyzer-0.0.1.dist-info/METADATA
RegexAnalyzer-0.0.1.dist-info/WHEEL
RegexAnalyzer-0.0.1.dist-info/entry_points.txt
RegexAnalyzer-0.0.1.dist-info/top_level.txt
RegexAnalyzer-0.0.1.dist-info/RECORD
